{"internationalTeamFlag":"x","mainFacts":{"id":"3262","fullName":"Deutscher Fußball-Bund e. V.","street":"Otto-Fleck-Schneise 6","postalCode":"60528","city":"Frankfurt (Main)","phone":"+49 (69) 6788-0","fax":"+49 (69) 6788-266","homepage":"www.dfb.de","founding":"Jan 28, 1900","members":"0","membersDate":"May 10, 2013","countryName":"Germany","countryID":"40","countryImage":"https://tmssl.akamaized.net/images/flagge/verysmall/40.png?lm=1520612525","avgAge":"27.30","squadSize":"26","legionaries":"6","internationalRank":11,"nationalPlayer":""},"stadium":{"id":"","name":"","street":"","postalCode":"","city":"","phoneTicketCenter":"","faxTicketCenter":"","homepage":"","ticketCenter":"","constructionYear":"","totalCapacity":"","standingRoom":"","seats":"","image":""},"historicImages":["https://tmssl.akamaized.net/images/wappen/medium/3262_1402756920.png?lm=1402756920","https://tmssl.akamaized.net/images/wappen/medium/3262_1402756949.png?lm=1402756949","https://tmssl.akamaized.net/images/wappen/medium/3262_1402756981.png?lm=1402756981","https://tmssl.akamaized.net/images/wappen/medium/3262_1402757020.png?lm=1402757020","https://tmssl.akamaized.net/images/wappen/medium/3262_1402757043.png?lm=1402757043"],"successes":[{"number":"4","name":"World Cup winner","id":"101","additionalData":{"competitionId":"WM22","competitionTypeId":"11","cycle":null,"seasonIds":["2013","1989","1973","1953"]}},{"number":"3","name":"European Champion","id":"102","additionalData":{"competitionId":"EM20","competitionTypeId":"11","cycle":null,"seasonIds":["1995","1979","1971"]}},{"number":"1","name":"Confederations Cup Champion","id":"103","additionalData":{"competitionId":"CC17","competitionTypeId":"11","cycle":"x","seasonIds":["2016"]}}],"additionalTeams":[{"image":"https://tmssl.akamaized.net/images/wappen/medium/3262.png?lm=1622018129","name":"Germany","id":"3262"},{"image":"https://tmssl.akamaized.net/images/wappen/medium/100200.png?lm=1655822948","name":"West Germany B","id":"100200"},{"image":"https://tmssl.akamaized.net/images/wappen/medium/3817.png?lm=1622018130","name":"Germany U21","id":"3817"},{"image":"https://tmssl.akamaized.net/images/wappen/medium/5709.png?lm=1622018130","name":"Germany U20","id":"5709"},{"image":"https://tmssl.akamaized.net/images/wappen/medium/5710.png?lm=1622018130","name":"Germany U19","id":"5710"},{"image":"https://tmssl.akamaized.net/images/wappen/medium/9067.png?lm=1622018130","name":"Germany U18","id":"9067"},{"image":"https://tmssl.akamaized.net/images/wappen/medium/17662.png?lm=1622018131","name":"Germany U17","id":"17662"},{"image":"https://tmssl.akamaized.net/images/wappen/medium/17368.png?lm=1622018131","name":"Germany U16","id":"17368"},{"image":"https://tmssl.akamaized.net/images/wappen/medium/49503.png?lm=1626352495","name":"Germany Olympic Team","id":"49503"},{"image":"https://tmssl.akamaized.net/images/wappen/medium/40791.png?lm=1622018132","name":"Germany Team 2006","id":"40791"}],"share":{"title":"Club profile Germany","url":"https://www.transfermarkt.com/germany/startseite/verein/3262","description":"This is the club's info page. Finf the current squad, relevant news, the latest rumours and all important information about the club."}}